google_account_client/__init__.py
google_account_client/test.py
google_account_client/test_simple.py
google_account_client/src/__init__.py
google_account_client/src/models/__init__.py
google_account_client/src/models/factory/__init__.py
google_account_client/src/models/factory/google_account_factory.py
google_account_client/src/models/google_account/__init__.py
google_account_client/src/models/google_account/google_account.py
google_account_client/src/models/google_account/google_calendar.py
google_account_client/src/models/service_handler/__init__.py
google_account_client/src/models/service_handler/oauth_service.py
google_account_client/src/models/service_handler/token_loader.py
google_account_client/src/settings/__init__.py
google_account_client/src/settings/config.py
google_account_client/src/settings/packages.py
google_account_client/src/utils/__init__.py
google_account_client/src/utils/logger.py
google_account_client/src/utils/token_validator.py
google_account_client-2.0.0.dist-info/METADATA
google_account_client-2.0.0.dist-info/WHEEL
google_account_client-2.0.0.dist-info/top_level.txt
google_account_client-2.0.0.dist-info/RECORD
