Metadata-Version: 2.4
Name: google_account_client
Version: 2.0.0
Author: DIACDE - TJGO
License: CC BY-NC-SA 4.0
Requires-Python: >=3.9.4
Requires-Dist: google-api-python-client==2.126.0
Requires-Dist: google-auth==2.29.0
Requires-Dist: google-auth-oauthlib==1.2.0
Requires-Dist: requests==2.31.0
Requires-Dist: python-dateutil>=2.8.2
Dynamic: author
Dynamic: description
Dynamic: description-content-type
Dynamic: license
Dynamic: requires-dist
Dynamic: requires-python
